odoo8_addon_website_sale_default_country-8.0.1.0.0.99.dev1-py2.7-nspkg.pth
odoo8_addon_website_sale_default_country-8.0.1.0.0.99.dev1.dist-info/top_level.txt
odoo8_addon_website_sale_default_country-8.0.1.0.0.99.dev1.dist-info/WHEEL
odoo8_addon_website_sale_default_country-8.0.1.0.0.99.dev1.dist-info/RECORD
odoo8_addon_website_sale_default_country-8.0.1.0.0.99.dev1.dist-info/metadata.json
odoo8_addon_website_sale_default_country-8.0.1.0.0.99.dev1.dist-info/DESCRIPTION.rst
odoo8_addon_website_sale_default_country-8.0.1.0.0.99.dev1.dist-info/METADATA
odoo8_addon_website_sale_default_country-8.0.1.0.0.99.dev1.dist-info/namespace_packages.txt
odoo_addons/website_sale_default_country/__openerp__.py
odoo_addons/website_sale_default_country/__init__.py
odoo_addons/website_sale_default_country/README.rst
odoo_addons/website_sale_default_country/controllers/main.py
odoo_addons/website_sale_default_country/controllers/__init__.py
odoo_addons/website_sale_default_country/static/description/icon.png
