Metadata-Version: 2.0
Name: odoo8-addon-website-sale-default-country
Version: 8.0.1.0.0.99.dev1
Summary: Give a default value for country at checkout
Home-page: http://www.antiun.com
Author: UNKNOWN
Author-email: UNKNOWN
License: AGPL-3
Platform: UNKNOWN
Requires-Dist: odoo (<9.0a,>=8.0a)
Classifier: Programming Language :: Python :: 2.7
Classifier: Framework :: Odoo
Classifier: License :: OSI Approved :: GNU Affero General Public License v3
